tensor_array/__init__.py
tensor_array/activation.py
tensor_array/tensor2.cpython-312-powerpc64le-linux-gnu.so
tensor_array/core/__init__.py
tensor_array/core/constants.py
tensor_array/core/datatypes.py
tensor_array/core/operator.py
tensor_array/core/tensor.py
tensor_array/layers/__init__.py
tensor_array/layers/layer.py
tensor_array/layers/parameter.py
tensor_array/layers/attention/__init__.py
tensor_array/layers/attention/attention.py
tensor_array/layers/attention/transformer.py
tensor_array/layers/normalization/__init__.py
tensor_array/layers/normalization/normalization.py
tensor_array/layers/util/__init__.py
tensor_array/layers/util/activation.py
tensor_array/layers/util/linear.py
tensor_array/layers/util/sequential.py
tensorarray.libs/libtensorarray_core-b43d1511.so
tensorarray.libs/libtensorarray_layers-dd749ba3.so
tensorarray-0.0.9.dist-info/METADATA
tensorarray-0.0.9.dist-info/WHEEL
tensorarray-0.0.9.dist-info/top_level.txt
tensorarray-0.0.9.dist-info/RECORD
tensorarray-0.0.9.dist-info/licenses/LICENSE
