Metadata-Version: 2.4
Name: TensorArray
Version: 0.0.9
Summary: A machine learning package
Home-page: https://github.com/Tensor-Array/Tensor-Array-Python
Author: TensorArray-Creators
License: MIT
Classifier: Development Status :: 2 - Pre-Alpha
Classifier: Programming Language :: Python :: 3
Classifier: Programming Language :: Python :: 3.8
Classifier: Programming Language :: Python :: 3.9
Classifier: Programming Language :: Python :: 3.10
Classifier: Programming Language :: Python :: 3.11
Classifier: Programming Language :: Python :: 3.12
Classifier: Programming Language :: Python :: 3.13
Classifier: License :: OSI Approved :: MIT License
Classifier: Environment :: GPU :: NVIDIA CUDA :: 12
Requires-Python: >=3.8
License-File: LICENSE
Dynamic: author
Dynamic: classifier
Dynamic: description
Dynamic: description-content-type
Dynamic: home-page
Dynamic: license
Dynamic: license-file
Dynamic: requires-python
Dynamic: summary
